{
  "categorias": [
    {
      "titulo": "Games",
      "link": "",
      "cor": "#fa0d0d",
      "link_extra": {
        "text": "",
        "url": ""
      },
      "videos": [
        {
          "titulo": "Mortal Kombat 11 - O Filme (Dublado)",
          "url": "https://youtu.be/axkJpV5NZBI"
        },
        {
          "titulo": "Mortal Kombat 11 Aftermath - O Filme Dublado",
          "url": "https://youtu.be/-1QBM0OTFCY"
        },
        {
          "titulo": "MORTAL KOMBAT 11 Trailer (2019)",
          "url": "https://youtu.be/bxFoRCvEjUA"
        },
        {
          "titulo": "Top Gear Remix (Snes) - Track 1 Synthwave / Retrowave Remix",
          "url": "https://youtu.be/tA7a_EEgwrw?list=LL3TVi4t8pAPsrVyYUiHt7YA"
        },
        {
          "titulo": "Assassins Creed Valhalla",
          "url": "https://www.youtube.com/watch?v=KDfdjB9uL0U"
        },
        {
          "titulo": "Assassin's Creed Unity E3 2014 World Premiere Cinematic Trailer [EUROPE]",
          "url": "https://youtu.be/xzCEdSKMkdU"
        },
        {
          "titulo": "Gerudo Valley - The Legend of Zelda: Ocarina Of Time",
          "url": "https://youtu.be/0hEYvdMoF2g?list=LL3TVi4t8pAPsrVyYUiHt7YA"
        },
        {
          "titulo": "Arcade Longplay [370] Street Fighter II: The World Warrior",
          "url": "https://youtu.be/xI284D4y1q4"
        }
      ]
    },
    {
      "titulo": "Música",
      "cor": "#F2CB05",
      "link_extra": {
        "text": "",
        "url": "https://youtu.be/Lli99OmkPwM"
      },
      "videos": [
        {
          "titulo": "Metallica: Fade to Black (Toronto, Canada - November 29, 2016)",
          "url": "https://youtu.be/A-4K4SX0m70"
        },
        {
          "titulo": "The Game Of Thrones Theme Song | Custom Shop | Fender",
          "url": "https://youtu.be/6i0a7RDPkM8"
        },
        {
          "titulo": "AC/DC - Thunderstruck (Live At River Plate, December 2009)",
          "url": "https://youtu.be/n_GFN3a0yj0"
        },
        {
          "titulo": "Scorpions - Acoustic Medley (Live At Hellfest, 20.06.2015)",
          "url": "https://youtu.be/buTdDo71v3k"
        },
        {
          "titulo": "Red Hot Chili Peppers - Californication LIVE Slane",
          "url": "https://youtu.be/I2dyKtSbsbM"
        }
      ]
    },
    {
      "titulo": "Filmes",
      "cor": "#23A5D9",
      "link_extra": {
        "text": "",
        "url": ""
      },
      "videos": [
        {
          "titulo": "Cena dos Portais DUBLADO 4K | Vingadores: Ultimato (2019)",
          "url": "https://youtu.be/50opun0b51o"
        },
        {
          "titulo": "Assassin's Creed | Trailer Oficial | Legendado HD",
          "url": "https://youtu.be/jTgzJ79KDsg"
        },
        {
          "titulo": "A Chegada",
          "url": "https://www.youtube.com/watch?v=rNciXGzYZms"
        },
        {
          "titulo": "Interestellar",
          "url": "https://www.youtube.com/watch?v=frD_IiY_A3E"
        }
      ]
    },
    {
      "titulo": "Séries",
      "cor": "orange",
      "videos": [
        {
          "titulo": "FULL Uncut Aang vs. Fire Lord Ozai Final Battle 🔥| Avatar",
          "url": "https://youtu.be/kXShLPXfWZA"
        },
        {
          "titulo": "One Day at a Time Trailer Oficial Netflix HD",
          "url": "https://youtu.be/4DF4ad1nWgg"
        },
        {
          "titulo": "Arrow Season 8 Official Trailer - Comic Con 2019",
          "url": "https://youtu.be/2yrviapP5uY"
        },
        {
          "titulo": "Game of Thrones: Season 1 Trailer",
          "url": "https://youtu.be/gcTkNV5Vg1E"
        }
      ]
    },
    {
      "titulo": "Universo",
      "cor": "#371E59",
      "link_extra": {
        "text": "",
        "url": ""
      },
      "videos": [
        {
          "titulo": "Astronomia - Origens",
          "url": "https://youtu.be/HiNR74zi8qQ?list=PLUBR4s0w2cG1kyI2MDBJV0J3B5HuJoB7g"
        },
        {
          "titulo": "Buraco Negro | Nerdologia",
          "url": "https://youtu.be/ThG5RHBR7dA"
        },
        {
          "titulo": "Teoria das cordas | Astronomia #9",
          "url": "https://youtu.be/sYPkIWeEYtk?list=PLUBR4s0w2cG1kyI2MDBJV0J3B5HuJoB7g"
        },
        {
          "titulo": "BURACOS NEGROS, como eles surgem?",
          "url": "https://youtu.be/WvQlhMjGo4M"
        },
        {
          "titulo": "Quarta dimensão explicada por Carl Sagan",
          "url": "https://youtu.be/WMZNLy0hGEI"
        },
        {
          "titulo": "6 NEBULOSAS INCRÍVEIS QUE VOCÊ PRECISA CONHECER",
          "url": "https://youtu.be/WDrFwhT-Ps4"
        }
      ]
    },
    {
      "titulo": "Aprendendo a aprender tecnologia",
      "cor": "#341fea",
      "link_extra": {
        "text": "",
        "url": ""
      },
      "videos": [
        {
          "titulo": "Como estudar melhor?",
          "url": "https://www.youtube.com/watch?v=Is6c9KSGCbk&feature=youtu.be"
        },
        {
          "titulo": "Faculdade",
          "url": "https://www.youtube.com/watch?v=jw06H8esyzQ&feature=youtu.be"
        },
        {
          "titulo": "Frameworks",
          "url": "https://www.youtube.com/watch?v=QzDjdlF1BQI"
        },
        {
          "titulo": "A mágica do Aprendizado",
          "url": "https://www.youtube.com/watch?v=oTEXzpfEpPY"
        },
        {
          "titulo": "Como aprender a programar?",
          "url": "https://www.youtube.com/watch?v=MwCx2qKdbDw&feature=youtu.be"
        }
      ]
    }
  ]
}
